a12rta/__init__.py
a12rta/a12rta.py
a12rta-0.1.0.dist-info/METADATA
a12rta-0.1.0.dist-info/WHEEL
a12rta-0.1.0.dist-info/entry_points.txt
a12rta-0.1.0.dist-info/top_level.txt
a12rta-0.1.0.dist-info/RECORD
