Metadata-Version: 2.1
Name: a12rta
Version: 0.1.0
Summary: Script tails logs on N-boxes (ssh)
Author: Pawel Suchanecki
Author-email: Pawel.Suchanecki@gmail.com
Classifier: Development Status :: 3 - Alpha
Classifier: Intended Audience :: Developers
Classifier: License :: OSI Approved :: MIT License
Classifier: Operating System :: OS Independent
Classifier: Programming Language :: Python :: 3
Requires-Python: >=3.7
Requires-Dist: fabric (<3.0.0,>=2.5.0)
Requires-Dist: PyYAML (<6.0,>=5.4)
Requires-Dist: asyncio (<4.0,>=3.4.3)
Provides-Extra: dev
Requires-Dist: twine (<4.0,>=3.4) ; extra == 'dev'
